cellyzer/__init__.py
cellyzer/core.py
cellyzer/dashboard.py
cellyzer/io.py
cellyzer/matrix.py
cellyzer/tools.py
cellyzer/utils.py
cellyzer/visualization.py
cellyzer-1.1.4.dist-info/LICENSE
cellyzer-1.1.4.dist-info/METADATA
cellyzer-1.1.4.dist-info/WHEEL
cellyzer-1.1.4.dist-info/top_level.txt
cellyzer-1.1.4.dist-info/RECORD
