Metadata-Version: 2.1
Name: cellyzer
Version: 1.1.4
Summary: A CDR(Call Data Records) data analyzing library
Home-page: https://anjuchamantha.github.io/cellyzer---CDR-data-analyzer/
Author: Team Cellyzer
Author-email: chamantha97anju@gmail.com
License: MIT
Platform: UNKNOWN
Classifier: License :: OSI Approved :: MIT License
Classifier: Intended Audience :: Science/Research
Classifier: Programming Language :: Python :: 3.7
Requires-Dist: xlrd (==1.2.0)
Requires-Dist: numpy (==1.18.2)
Requires-Dist: tabulate (==0.8.7)
Requires-Dist: datetime (==4.3)
Requires-Dist: networkx (==2.4)
Requires-Dist: matplotlib (==3.2.1)
Requires-Dist: folium (==0.10.1)
Requires-Dist: IPython
